[
  {
    "name": "Intel Core i7-10700K",
    "category": "CPU",
    "price": 329.99,
    "status": "In Stock",
    "image": "https://images.unsplash.com/photo-1540829917886-91ab031b1764?ixlib=rb-4.0.3&ixid=M3wxMjA3fDB8MHxzZWFyY2h8M3x8cHJvY2Vzc29yfGVufDB8MHwwfHx8MA%3D%3D&auto=format&fit=crop&w=500&q=60",
    "description": "Intel Core i7 10th Gen unlocked processor for gaming and content creation.",
    "keyFeatures": {
      "Brand": "Intel",
      "Model": "Core i7-10700K",
      "Socket": "LGA1200",
      "Cores": "8",
      "Threads": "16",
      "Base Clock": "3.8 GHz",
      "Max Boost Clock": "5.1 GHz",
      "TDP": "125W"
    },
    "individualRating": 4.5,
    "averageRating": 4.3,
    "reviews": [
      {
        "username": "gamer123",
        "rating": 5,
        "comment": "Great CPU for gaming!"
      },
      {
        "username": "contentcreator",
        "rating": 4,
        "comment": "Handles video editing well."
      }
    ],
    "featured": true
  },
  {
    "name": "AMD Ryzen 9 5900X",
    "category": "CPU",
    "price": 549.99,
    "status": "In Stock",
    "image": "https://plus.unsplash.com/premium_photo-1681426701125-bed484a8c829?ixlib=rb-4.0.3&ixid=M3wxMjA3fDB8MHxzZWFyY2h8MTl8fHByb2Nlc3NvcnxlbnwwfDB8MHx8fDA%3D&auto=format&fit=crop&w=500&q=60",
    "description": "AMD Ryzen 9 5000 series processor with 12 cores and 24 threads.",
    "keyFeatures": {
      "Brand": "AMD",
      "Model": "Ryzen 9 5900X",
      "Socket": "AM4",
      "Cores": "12",
      "Threads": "24",
      "Base Clock": "3.7 GHz",
      "Max Boost Clock": "4.8 GHz",
      "TDP": "105W"
    },
    "individualRating": 4.8,
    "averageRating": 4.7,
    "reviews": [
      {
        "username": "gamer456",
        "rating": 5,
        "comment": "Excellent performance for multi-tasking."
      },
      {
        "username": "pcbuilder2000",
        "rating": 4,
        "comment": "Good for gaming setups."
      }
    ],
    "featured": false
  },
  {
    "name": "ASUS ROG Strix B550-F",
    "category": "Motherboard",
    "price": 189.99,
    "status": "In Stock",
    "image": "https://plus.unsplash.com/premium_photo-1681426669771-d2113672a49b?ixlib=rb-4.0.3&ixid=M3wxMjA3fDB8MHxzZWFyY2h8MTN8fG1vdGhlcmJvYXJkfGVufDB8MHwwfHx8MA%3D%3D&auto=format&fit=crop&w=500&q=60",
    "description": "High-performance ATX motherboard with PCIe 4.0 support.",
    "keyFeatures": {
      "Brand": "ASUS",
      "Model": "ROG Strix B550-F",
      "Form Factor": "ATX",
      "Socket": "AM4",
      "Memory Slots": "4",
      "Max Memory": "128GB",
      "PCIe Slots": "3 x16, 3 x1",
      "M.2 Slots": "2",
      "USB Ports": "8 x USB 3.2 Gen 1, 4 x USB 3.2 Gen 2"
    },
    "individualRating": 4.8,
    "averageRating": 4.7,
    "reviews": [
      {
        "username": "gamer123",
        "rating": 5,
        "comment": "Great features and performance."
      },
      {
        "username": "pcbuilder2000",
        "rating": 4,
        "comment": "Good for gaming setups."
      }
    ],
    "featured": true
  },
  {
    "name": "GIGABYTE B450M DS3H",
    "category": "Motherboard",
    "price": 79.99,
    "status": "In Stock",
    "image": "https://images.unsplash.com/photo-1522920192563-6df902920a8a?ixlib=rb-4.0.3&ixid=M3wxMjA3fDB8MHxzZWFyY2h8OXx8bW90aGVyYm9hcmR8ZW58MHwwfDB8fHww&auto=format&fit=crop&w=500&q=60",
    "description": "Budget-friendly Micro ATX motherboard with AMD B450 chipset.",
    "keyFeatures": {
      "Brand": "GIGABYTE",
      "Model": "B450M DS3H",
      "Form Factor": "Micro ATX",
      "Socket": "AM4",
      "Memory Slots": "4",
      "Max Memory": "64GB",
      "PCIe Slots": "1 x16, 1 x4, 1 x1",
      "M.2 Slots": "1",
      "USB Ports": "4 x USB 3.1 Gen 1, 2 x USB 2.0"
    },
    "individualRating": 4.2,
    "averageRating": 4.0,
    "reviews": [
      {
        "username": "budgetgamer",
        "rating": 4,
        "comment": "Good value for the price."
      },
      {
        "username": "casualuser",
        "rating": 3,
        "comment": "Decent features for an entry-level build."
      }
    ],
    "featured": false
  },
  {
    "name": "Corsair Vengeance LPX 16GB",
    "category": "RAM",
    "price": 89.99,
    "status": "In Stock",
    "image": "https://images.unsplash.com/photo-1592664474505-51c549ad15c5?ixlib=rb-4.0.3&ixid=M3wxMjA3fDB8MHxzZWFyY2h8Mnx8cmFtfGVufDB8MHwwfHx8MA%3D%3D&auto=format&fit=crop&w=500&q=60",
    "description": "16GB DDR4 memory module for high-speed performance.",
    "keyFeatures": {
      "Brand": "Corsair",
      "Model": "Vengeance LPX",
      "Capacity": "16GB (2x8GB)",
      "Speed": "3200MHz",
      "Timing": "16-18-18-36",
      "Voltage": "1.35V",
      "Color": "Black"
    },
    "individualRating": 4.6,
    "averageRating": 4.4,
    "reviews": [
      {
        "username": "gamerXYZ",
        "rating": 5,
        "comment": "Fast and reliable RAM for gaming."
      },
      {
        "username": "pcenthusiast",
        "rating": 4,
        "comment": "Good value for the price."
      }
    ],
    "featured": true
  },
  {
    "name": "G.SKILL Trident Z RGB 32GB",
    "category": "RAM",
    "price": 189.99,
    "status": "In Stock",
    "image": "https://images.unsplash.com/photo-1592664474505-51c549ad15c5?ixlib=rb-4.0.3&ixid=M3wxMjA3fDB8MHxzZWFyY2h8Mnx8cmFtfGVufDB8MHwwfHx8MA%3D%3D&auto=format&fit=crop&w=500&q=60",
    "description": "32GB DDR4 memory module with RGB lighting for high-performance and aesthetics.",
    "keyFeatures": {
      "Brand": "G.SKILL",
      "Model": "Trident Z RGB",
      "Capacity": "32GB (2x16GB)",
      "Speed": "3600MHz",
      "Timing": "16-19-19-39",
      "Voltage": "1.35V",
      "Color": "Black",
      "RGB": "Yes"
    },
    "individualRating": 4.7,
    "reviews": [
      {
        "username": "rgblover",
        "rating": 5,
        "comment": "Stunning RGB effects and excellent performance."
      },
      {
        "username": "gamemaster",
        "rating": 5,
        "comment": "Fast and stable RAM for gaming and multitasking."
      }
    ],
    "featured": false
  },
  {
    "name": "Wacom Intuos Pro",
    "category": "Others",
    "price": 349.99,
    "status": "In Stock",
    "image": "/images/other2.jpg",
    "description": "Professional graphics tablet with pressure sensitivity and customizable keys.",
    "keyFeatures": {
      "Brand": "Wacom",
      "Model": "Intuos Pro",
      "Active Area": "Medium (8.7 x 5.8 inches)",
      "Pressure Levels": "8192",
      "Express Keys": "8",
      "Touch Ring": "Yes",
      "Pen Technology": "Battery-free EMR",
      "Compatibility": "Windows, macOS"
    },
    "individualRating": 4.8,
    "averageRating": 4.7,
    "reviews": [
      {
        "username": "graphicdesigner",
        "rating": 5,
        "comment": "Precise and responsive pen tablet for design work."
      },
      {
        "username": "artistatwork",
        "rating": 4,
        "comment": "Great tool for digital art and illustration."
      }
    ],
    "featured": false
  }
]
